<program>
  <assign to="x">
    <add>
      <var>x</var>
      <integer>4</integer>
    </add>
  </assign>

  <assign to="v">
    <vector>
      <row>
        <integer>1</integer>
        <integer>2</integer>
        <integer>3</integer>
        <integer>4</integer>
      </row>
    </vector>
  </assign>

  <assign to="w">
    <generate>
      <size>
        <var>x</var>
      </size>
      <low>
        <integer>1</integer>
      </low>
      <high>
        <integer>5</integer>
      </high>
    </generate>
  </assign>

  <assign to="z">
    <add>
      <var>v</var>
      <var>w</var>
    </add>
  </assign>

  <return>
    <integer>0</integer>
  </return>
</program>